{
    "alarms": [
        {
            "index": 5006,
            "cause": "UNDERLYING_RESOURCE_UNAVAILABLE",
            "name": "MEMENTO_AS_CASSANDRA_COMM_ERROR",
            "levels": [
                {
                    "severity": "CLEARED",
                    "details": "Memento Application Server communication to the local Cassandra has been restored.",
                    "description": "Memento: Application Server Cassandra communication error cleared",
                    "cause": "Memento Application Server communication to the local Cassandra has been restored. The previously issued alarm has been cleared.",
                    "effect": "Normal Memento Application Server operation has been restored.",
                    "action": "No action."
                },
                {
                    "severity": "CRITICAL",
                    "details": "While this condition persists, new call list records will not be written and will be lost. The Application Server will periodically attempt to reconnect.",
                    "description": "Memento: Application Server Cassandra communication error",
                    "cause": "Memento Application Server is unable to contact the local Cassandra.",
                    "effect": "While this condition persists, new call list records will not be written and will be lost.",
                    "action": "Monitor for the alarm to clear and confirm the system is operating normally. Determine if the local Cassandra process has failed. If it has then make sure it returns to service. If the alarm doesn't clear then contact your support representative."
                }
            ]
        }
    ]
}
